fintech/__init__.py
fintech/blueprints/admin/__init__.py
fintech/blueprints/admin/algos.py
fintech/blueprints/admin/forms.py
fintech/blueprints/admin/patterns.py
fintech/blueprints/admin/rolling_window.py
fintech/blueprints/admin/static/assets/css/style.css
fintech/blueprints/admin/static/assets/img/not-found.svg
fintech/blueprints/admin/static/assets/img/favicons/android-chrome-192x192.png
fintech/blueprints/admin/static/assets/img/favicons/android-chrome-512x512.png
fintech/blueprints/admin/static/assets/img/favicons/apple-touch-icon.png
fintech/blueprints/admin/static/assets/img/favicons/favicon-16x16.png
fintech/blueprints/admin/static/assets/img/favicons/favicon-32x32.png
fintech/blueprints/admin/static/assets/img/favicons/favicon.ico
fintech/blueprints/admin/static/assets/img/touch-icons/apple-touch-icon-ipad-76x76.png
fintech/blueprints/admin/static/assets/img/touch-icons/apple-touch-icon-ipad-retina-152x152.png
fintech/blueprints/admin/static/assets/img/touch-icons/apple-touch-icon-iphone-60x60.png
fintech/blueprints/admin/static/assets/img/touch-icons/apple-touch-icon-iphone-retina-120x120.png
fintech/blueprints/admin/static/assets/js/main.js
fintech/blueprints/admin/static/assets/vendor/bootstrap/css/bootstrap-grid.css
fintech/blueprints/admin/static/assets/vendor/bootstrap/css/bootstrap-grid.css.map
fintech/blueprints/admin/static/assets/vendor/bootstrap/css/bootstrap-grid.min.css
fintech/blueprints/admin/static/assets/vendor/bootstrap/css/bootstrap-grid.min.css.map
fintech/blueprints/admin/static/assets/vendor/bootstrap/css/bootstrap-grid.rtl.css
fintech/blueprints/admin/static/assets/vendor/bootstrap/css/bootstrap-grid.rtl.css.map
fintech/blueprints/admin/static/assets/vendor/bootstrap/css/bootstrap-grid.rtl.min.css
fintech/blueprints/admin/static/assets/vendor/bootstrap/css/bootstrap-grid.rtl.min.css.map
fintech/blueprints/admin/static/assets/vendor/bootstrap/css/bootstrap-reboot.css
fintech_webserver-1.0.1.dist-info/METADATA
fintech_webserver-1.0.1.dist-info/WHEEL
fintech_webserver-1.0.1.dist-info/entry_points.txt
fintech_webserver-1.0.1.dist-info/top_level.txt
fintech_webserver-1.0.1.dist-info/RECORD
