Metadata-Version: 2.1
Name: fintech_webserver
Version: 1.0.1
Summary: A webapp with different stock market analysis features made with Flask.
Author-email: Soham Jobanputra <sohamjobanputra7@gmail.com>
Project-URL: Repository, https://github.com/Soham7777777/Fintech.git
Requires-Python: >=3.10
Requires-Dist: Flask==3.0.3
Requires-Dist: python-dotenv==1.0.1
Requires-Dist: Flask-WTF==1.2.2
Requires-Dist: pandas==2.2.3
Requires-Dist: matplotlib==3.9.3
Requires-Dist: mpld3==0.5.10
